core_common_configuration/__init__.py
core_common_configuration/app_conf.py
core_common_configuration/base_conf.py
core_common_configuration/base_conf_env.py
core_common_configuration/base_conf_manager.py
core_common_configuration/py.typed
core_common_configuration/service_conf_manager.py
turintech_configuration-2.0.1.dist-info/METADATA
turintech_configuration-2.0.1.dist-info/WHEEL
turintech_configuration-2.0.1.dist-info/licenses/LICENSE
turintech_configuration-2.0.1.dist-info/RECORD
