Metadata-Version: 2.4
Name: turintech_configuration
Version: 2.0.1
Summary: A library for common configuration
License-Expression: LicenseRef-Turing-Intelligence-Technology-EULA
License-File: LICENSE
Classifier: Development Status :: 5 - Production/Stable
Classifier: License :: Other/Proprietary License
Requires-Python: <3.14,>=3.8
Requires-Dist: pydantic-settings<3,>=2
Requires-Dist: pydantic<3.0.0,>=2
Requires-Dist: python-dotenv<1.0.0,>=0.21.0
Requires-Dist: turintech-data-types<3.0.0,>=2.0.0a0
